mask_predictor/__init__.py
mask_predictor/mask_predictor.py
mask_predictor-0.0.9.dist-info/LICENSE
mask_predictor-0.0.9.dist-info/METADATA
mask_predictor-0.0.9.dist-info/WHEEL
mask_predictor-0.0.9.dist-info/top_level.txt
mask_predictor-0.0.9.dist-info/RECORD
